<?xml version="1.0" encoding="utf-8" ?><dwsync><file name="ourstore1.jpg" server="kitchenartcanada.com" local="3471464426" remote="12139507592" /><file name="IMG_2884.jpg" server="kitchenartcanada.com" local="3465757523" remote="12139507592" /><file name="IMG_2884a.jpg" server="kitchenartcanada.com" local="3465762871" remote="12139507592" /><file name="IMG_2885.jpg" server="kitchenartcanada.com" local="3465757505" remote="12139507592" /><file name="IMG_2914.jpg" server="kitchenartcanada.com" local="3465757485" remote="12139507592" /><file name="IMG_2938.jpg" server="kitchenartcanada.com" local="3465757454" remote="12139507592" /><file name="IMG_5355.jpg" server="kitchenartcanada.com" local="3465757535" remote="12139507592" /><file name="IMG_5357.jpg" server="kitchenartcanada.com" local="3465757431" remote="12139507592" /><file name="IMG_5360.jpg" server="kitchenartcanada.com" local="3465757417" remote="12139507592" /><file name="IMG_5361.jpg" server="kitchenartcanada.com" local="3465757406" remote="12139507592" /><file name="IMG_5363.jpg" server="kitchenartcanada.com" local="3465757398" remote="12139507592" /><file name="IMG_5365.jpg" server="kitchenartcanada.com" local="3465757391" remote="12139507592" /><file name="IMG_5372.jpg" server="kitchenartcanada.com" local="3465757377" remote="12139507592" /><file name="IMG_5494.jpg" server="kitchenartcanada.com" local="3465757367" remote="12139507592" /><file name="IMG_5497.jpg" server="kitchenartcanada.com" local="3465757355" remote="12139507592" /><file name="ourstore.jpg" server="kitchenartcanada.com" local="3471300633" remote="12139507592" /><file name="IMG_2884.jpg" server="kitchenartcanada.com//public_html/" local="3465757523" remote="12139735292" /><file name="IMG_2884a.jpg" server="kitchenartcanada.com//public_html/" local="3465762871" remote="12139735292" /><file name="IMG_2885.jpg" server="kitchenartcanada.com//public_html/" local="3465757505" remote="12139735292" /><file name="IMG_2914.jpg" server="kitchenartcanada.com//public_html/" local="3465757485" remote="12139735292" /><file name="IMG_2938.jpg" server="kitchenartcanada.com//public_html/" local="3465757454" remote="12139735292" /><file name="IMG_5355.jpg" server="kitchenartcanada.com//public_html/" local="3465757535" remote="12139735292" /><file name="IMG_5357.jpg" server="kitchenartcanada.com//public_html/" local="3465757431" remote="12139735292" /><file name="IMG_5360.jpg" server="kitchenartcanada.com//public_html/" local="3465757417" remote="12139735292" /><file name="IMG_5361.jpg" server="kitchenartcanada.com//public_html/" local="3465757406" remote="12139735292" /><file name="IMG_5363.jpg" server="kitchenartcanada.com//public_html/" local="3465757398" remote="12139735292" /><file name="IMG_5365.jpg" server="kitchenartcanada.com//public_html/" local="3465757391" remote="12139735292" /><file name="IMG_5372.jpg" server="kitchenartcanada.com//public_html/" local="3465757377" remote="12139735292" /><file name="IMG_5494.jpg" server="kitchenartcanada.com//public_html/" local="3465757367" remote="12139735292" /><file name="IMG_5497.jpg" server="kitchenartcanada.com//public_html/" local="3465757355" remote="12139735292" /><file name="ourstore.jpg" server="kitchenartcanada.com//public_html/" local="3471300633" remote="12139735292" /><file name="ourstore1.jpg" server="kitchenartcanada.com//public_html/" local="3471464426" remote="12139735292" /></dwsync>