<?xml version="1.0" encoding="utf-8" ?><dwsync><file name="beatrizball.jpg" server="testingka.zzl.org" local="3465495305" remote="12061260932" /><file name="bosch175.jpg" server="testingka.zzl.org" local="3465328151" remote="12061260932" /><file name="chefn175.jpg" server="testingka.zzl.org" local="3465328334" remote="12061260932" /><file name="cobblehill.jpg" server="testingka.zzl.org" local="3467828023" remote="12061260932" /><file name="corolle.jpg" server="testingka.zzl.org" local="3467827988" remote="12061260932" /><file name="guzzini175.jpg" server="testingka.zzl.org" local="3465328536" remote="12061260932" /><file name="klutz.jpg" server="testingka.zzl.org" local="3465338435" remote="12061260932" /><file name="kuhnrikon.jpg" server="testingka.zzl.org" local="3465338777" remote="12061260932" /><file name="l-objet.jpg" server="testingka.zzl.org" local="3467144857" remote="12061260932" /><file name="ladyjayne.jpg" server="testingka.zzl.org" local="3467145254" remote="12061260932" /><file name="leonardo.jpg" server="testingka.zzl.org" local="3465406674" remote="12061260932" /><file name="magicmill.jpg" server="testingka.zzl.org" local="3465406654" remote="12061260932" /><file name="melissaanddoug.jpg" server="testingka.zzl.org" local="3465406614" remote="12061260992" /><file name="metalacelogo1175.jpg" server="testingka.zzl.org" local="3465940982" remote="12061260992" /><file name="microplane.jpg" server="testingka.zzl.org" local="3467827446" remote="12061260992" /><file name="moser.jpg" server="testingka.zzl.org" local="3466117115" remote="12061260992" /><file name="nachtmann.jpg" server="testingka.zzl.org" local="3465406549" remote="12061260992" /><file name="nordicware.jpg" server="testingka.zzl.org" local="3467144731" remote="12061260992" /><file name="nowdesigns.jpg" server="testingka.zzl.org" local="3467145214" remote="12061260992" /><file name="oliviariegel.jpg" server="testingka.zzl.org" local="3465407645" remote="12061260992" /><file name="orchardtoys.jpg" server="testingka.zzl.org" local="3465406525" remote="12061260992" /><file name="oxo.jpg" server="testingka.zzl.org" local="3465406496" remote="12061260992" /><file name="portmeirion.jpg" server="testingka.zzl.org" local="3465406430" remote="12061260992" /><file name="quercetti.jpg" server="testingka.zzl.org" local="3465406349" remote="12061260992" /><file name="rainbowloom.jpg" server="testingka.zzl.org" local="3467826305" remote="12061260992" /><file name="ravensburger.jpg" server="testingka.zzl.org" local="3465406307" remote="12061260992" /><file name="rsvp.jpg" server="testingka.zzl.org" local="3465406278" remote="12061260992" /><file name="sagaform.jpg" server="testingka.zzl.org" local="3465406187" remote="12061260992" /><file name="tinylove.jpg" server="testingka.zzl.org" local="3465406117" remote="12061260992" /><file name="tramontina.jpg" server="testingka.zzl.org" local="3465406080" remote="12061260992" /><file name="victorinox.jpg" server="testingka.zzl.org" local="3472062199" remote="12062020892" /><file name="wilton.jpg" server="testingka.zzl.org" local="3467144928" remote="12061260992" /><file name="yamazaki.jpg" server="testingka.zzl.org" local="3465405915" remote="12061260992" /><file name="zyliss.jpg" server="testingka.zzl.org" local="3465405886" remote="12061260992" /><file name="artscroll.jpg" server="testingka.zzl.org" local="3467145351" remote="12061348172" /><file name="bosch470.jpg" server="testingka.zzl.org" local="3465328169" remote="12061348172" /><file name="chefn470.jpg" server="testingka.zzl.org" local="3465328348" remote="12061348172" /><file name="feldheim.jpg" server="testingka.zzl.org" local="3467145055" remote="12061348172" /><file name="guzzini470.jpg" server="testingka.zzl.org" local="3465328557" remote="12061348172" /><file name="lenox175.jpg" server="testingka.zzl.org" local="3465338168" remote="12061348172" /><file name="productlink4a.png" server="testingka.zzl.org" local="3465339643" remote="12061348172" /><file name="yairemanuel.jpg" server="testingka.zzl.org" local="3471376331" remote="12061328852" /><file name="casafina.jpg" server="testingka.zzl.org" local="3472065298" remote="12062020892" /><file name="koziol.jpg" server="testingka.zzl.org" local="3472065248" remote="12062020892" /><file name="lenox.jpg" server="testingka.zzl.org" local="3472065207" remote="12062020892" /><file name="magna-tiles.jpg" server="testingka.zzl.org" local="3472065143" remote="12062020892" /><file name="maryjurek.jpg" server="testingka.zzl.org" local="3472065132" remote="12062020892" /><file name="quest.jpg" server="testingka.zzl.org" local="3472065094" remote="12062020892" /><file name="sistema.jpg" server="testingka.zzl.org" local="3472064939" remote="12062020892" /><file name="smartgames.jpg" server="testingka.zzl.org" local="3472064898" remote="12062020892" /><file name="thinkfun.jpg" server="testingka.zzl.org" local="3472066596" remote="12062020892" /><file name="vidivi.jpg" server="testingka.zzl.org" local="3472064868" remote="12062020892" /><file name="Badash.jpg" server="testingka.zzl.org" local="3472134916" remote="12062100632" /><file name="janod.jpg" server="testingka.zzl.org" local="3472135365" remote="12062100632" /><file name="rcrcrystal.jpg" server="testingka.zzl.org" local="3472135200" remote="12062100632" /><file name="Rogaska.jpg" server="testingka.zzl.org" local="3472149175" remote="12062101652" /><file name="zoku.jpg" server="testingka.zzl.org" local="3472149089" remote="12062101652" /><file name="djeco.jpg" server="testingka.zzl.org" local="3472403579" remote="12062366972" /><file name="cuisipro.jpg" server="testingka.zzl.org" local="3472491325" remote="12062444252" /><file name="dabbah.jpg" server="testingka.zzl.org" local="3472491741" remote="12062444252" /><file name="juliaknight.jpg" server="testingka.zzl.org" local="3472491811" remote="12062444252" /><file name="luminarc.jpg" server="testingka.zzl.org" local="3472491463" remote="12062444252" /><file name="mora.jpg" server="testingka.zzl.org" local="3472491516" remote="12062444252" /><file name="plusplus.jpg" server="testingka.zzl.org" local="3472491211" remote="12062444252" /><file name="royalworcester.jpg" server="testingka.zzl.org" local="3472491603" remote="12062444252" /><file name="wildeye.jpg" server="testingka.zzl.org" local="3472491660" remote="12062444252" /><file name="clics.jpg" server="testingka.zzl.org" local="3472493095" remote="12062445512" /><file name="Badash.jpg" server="kitchenartcanada.com" local="3472134916" remote="12139503752" /><file name="beatrizball.jpg" server="kitchenartcanada.com" local="3465495305" remote="12139503752" /><file name="bosch175.jpg" server="kitchenartcanada.com" local="3465328151" remote="12139503752" /><file name="casafina.jpg" server="kitchenartcanada.com" local="3472065298" remote="12139503752" /><file name="chefn175.jpg" server="kitchenartcanada.com" local="3465328334" remote="12139503752" /><file name="clics.jpg" server="kitchenartcanada.com" local="3472493095" remote="12139503752" /><file name="cobblehill.jpg" server="kitchenartcanada.com" local="3467828023" remote="12139503752" /><file name="corolle.jpg" server="kitchenartcanada.com" local="3467827988" remote="12139503752" /><file name="cuisipro.jpg" server="kitchenartcanada.com" local="3472491325" remote="12139503752" /><file name="dabbah.jpg" server="kitchenartcanada.com" local="3472491741" remote="12139503752" /><file name="djeco.jpg" server="kitchenartcanada.com" local="3472403579" remote="12139503752" /><file name="guzzini175.jpg" server="kitchenartcanada.com" local="3465328536" remote="12139503752" /><file name="janod.jpg" server="kitchenartcanada.com" local="3472135365" remote="12139503752" /><file name="juliaknight.jpg" server="kitchenartcanada.com" local="3472491811" remote="12139503752" /><file name="klutz.jpg" server="kitchenartcanada.com" local="3465338435" remote="12139503752" /><file name="koziol.jpg" server="kitchenartcanada.com" local="3472065248" remote="12139503752" /><file name="kuhnrikon.jpg" server="kitchenartcanada.com" local="3465338777" remote="12139503752" /><file name="l-objet.jpg" server="kitchenartcanada.com" local="3467144857" remote="12139503752" /><file name="lenox.jpg" server="kitchenartcanada.com" local="3472065207" remote="12139503752" /><file name="leonardo.jpg" server="kitchenartcanada.com" local="3465406674" remote="12139503752" /><file name="luminarc.jpg" server="kitchenartcanada.com" local="3472491463" remote="12139503752" /><file name="magicmill.jpg" server="kitchenartcanada.com" local="3465406654" remote="12139503752" /><file name="magna-tiles.jpg" server="kitchenartcanada.com" local="3472065143" remote="12139503752" /><file name="maryjurek.jpg" server="kitchenartcanada.com" local="3472065132" remote="12139503752" /><file name="melissaanddoug.jpg" server="kitchenartcanada.com" local="3465406614" remote="12139503752" /><file name="metalacelogo1175.jpg" server="kitchenartcanada.com" local="3465940982" remote="12139503752" /><file name="microplane.jpg" server="kitchenartcanada.com" local="3467827446" remote="12139503752" /><file name="mora.jpg" server="kitchenartcanada.com" local="3472491516" remote="12139503752" /><file name="moser.jpg" server="kitchenartcanada.com" local="3466117115" remote="12139503752" /><file name="nachtmann.jpg" server="kitchenartcanada.com" local="3465406549" remote="12139503752" /><file name="nordicware.jpg" server="kitchenartcanada.com" local="3467144731" remote="12139503752" /><file name="oliviariegel.jpg" server="kitchenartcanada.com" local="3465407645" remote="12139503752" /><file name="orchardtoys.jpg" server="kitchenartcanada.com" local="3465406525" remote="12139503752" /><file name="oxo.jpg" server="kitchenartcanada.com" local="3465406496" remote="12139503752" /><file name="plusplus.jpg" server="kitchenartcanada.com" local="3472491211" remote="12139503752" /><file name="portmeirion.jpg" server="kitchenartcanada.com" local="3465406430" remote="12139503752" /><file name="quercetti.jpg" server="kitchenartcanada.com" local="3465406349" remote="12139503812" /><file name="quest.jpg" server="kitchenartcanada.com" local="3472065094" remote="12139503812" /><file name="rainbowloom.jpg" server="kitchenartcanada.com" local="3467826305" remote="12139503812" /><file name="ravensburger.jpg" server="kitchenartcanada.com" local="3465406307" remote="12139503812" /><file name="rsvp.jpg" server="kitchenartcanada.com" local="3465406278" remote="12139503812" /><file name="rcrcrystal.jpg" server="kitchenartcanada.com" local="3472135200" remote="12139503812" /><file name="Rogaska.jpg" server="kitchenartcanada.com" local="3472149175" remote="12139503812" /><file name="royalworcester.jpg" server="kitchenartcanada.com" local="3473115810" remote="12139503812" /><file name="sagaform.jpg" server="kitchenartcanada.com" local="3465406187" remote="12139503812" /><file name="smartgames.jpg" server="kitchenartcanada.com" local="3472064898" remote="12139503812" /><file name="thinkfun.jpg" server="kitchenartcanada.com" local="3472066596" remote="12139503812" /><file name="tinylove.jpg" server="kitchenartcanada.com" local="3465406117" remote="12139503812" /><file name="tramontina.jpg" server="kitchenartcanada.com" local="3465406080" remote="12139503812" /><file name="victorinox.jpg" server="kitchenartcanada.com" local="3472062199" remote="12139503812" /><file name="vidivi.jpg" server="kitchenartcanada.com" local="3472064868" remote="12139503812" /><file name="wildeye.jpg" server="kitchenartcanada.com" local="3472491660" remote="12139503812" /><file name="wilton.jpg" server="kitchenartcanada.com" local="3467144928" remote="12139503812" /><file name="yairemanuel.jpg" server="kitchenartcanada.com" local="3471376331" remote="12139503812" /><file name="yamazaki.jpg" server="kitchenartcanada.com" local="3465405915" remote="12139503812" /><file name="zoku.jpg" server="kitchenartcanada.com" local="3472149089" remote="12139503812" /><file name="zyliss.jpg" server="kitchenartcanada.com" local="3465405886" remote="12139503812" /><file name=".DS_Store" server="kitchenartcanada.com" local="3472491885" remote="12139503752" /><file name="artscroll.jpg" server="kitchenartcanada.com" local="3467145351" remote="12139503752" /><file name="bosch470.jpg" server="kitchenartcanada.com" local="3465328169" remote="12139503752" /><file name="chefn470.jpg" server="kitchenartcanada.com" local="3465328348" remote="12139503752" /><file name="feldheim.jpg" server="kitchenartcanada.com" local="3467145055" remote="12139503752" /><file name="guzzini470.jpg" server="kitchenartcanada.com" local="3465328557" remote="12139503752" /><file name="ladyjayne.jpg" server="kitchenartcanada.com" local="3467145254" remote="12139503752" /><file name="lenox175.jpg" server="kitchenartcanada.com" local="3465338168" remote="12139503752" /><file name="nowdesigns.jpg" server="kitchenartcanada.com" local="3467145214" remote="12139503752" /><file name="productlink4a.png" server="kitchenartcanada.com" local="3465339643" remote="12139503812" /><file name="rcr.jpg" server="kitchenartcanada.com" local="3472065061" remote="12139503812" /><file name="sistema.jpg" server="kitchenartcanada.com" local="3472064939" remote="12139503812" /><file name="splendide.jpg" server="kitchenartcanada.com" local="3472562160" remote="12139503812" /><file name="steelforme.jpg" server="kitchenartcanada.com" local="3497308193" remote="12139503812" /><file name="michaelwainwright.jpg" server="kitchenartcanada.com" local="3497309487" remote="12139503752" /><file name="inspiredgenerations.jpg" server="kitchenartcanada.com" local="3514142865" remote="12139503752" /><file name="spicebox.jpg" server="kitchenartcanada.com" local="3539037193" remote="12139503812" /><file name=".DS_Store" server="kitchenartcanada.com//public_html/" local="3472491885" remote="12139730972" /><file name="artscroll.jpg" server="kitchenartcanada.com//public_html/" local="3467145351" remote="12139730972" /><file name="Badash.jpg" server="kitchenartcanada.com//public_html/" local="3472134916" remote="12139730972" /><file name="beatrizball.jpg" server="kitchenartcanada.com//public_html/" local="3465495305" remote="12139730972" /><file name="bosch175.jpg" server="kitchenartcanada.com//public_html/" local="3465328151" remote="12139730972" /><file name="bosch470.jpg" server="kitchenartcanada.com//public_html/" local="3465328169" remote="12139730972" /><file name="casafina.jpg" server="kitchenartcanada.com//public_html/" local="3472065298" remote="12139730972" /><file name="chefn175.jpg" server="kitchenartcanada.com//public_html/" local="3465328334" remote="12139730972" /><file name="chefn470.jpg" server="kitchenartcanada.com//public_html/" local="3465328348" remote="12139730972" /><file name="clics.jpg" server="kitchenartcanada.com//public_html/" local="3472493095" remote="12139730972" /><file name="cobblehill.jpg" server="kitchenartcanada.com//public_html/" local="3467828023" remote="12139730972" /><file name="corolle.jpg" server="kitchenartcanada.com//public_html/" local="3467827988" remote="12139730972" /><file name="cuisipro.jpg" server="kitchenartcanada.com//public_html/" local="3472491325" remote="12139730972" /><file name="dabbah.jpg" server="kitchenartcanada.com//public_html/" local="3472491741" remote="12139730972" /><file name="djeco.jpg" server="kitchenartcanada.com//public_html/" local="3472403579" remote="12139730972" /><file name="feldheim.jpg" server="kitchenartcanada.com//public_html/" local="3467145055" remote="12139730972" /><file name="guzzini175.jpg" server="kitchenartcanada.com//public_html/" local="3465328536" remote="12139730972" /><file name="guzzini470.jpg" server="kitchenartcanada.com//public_html/" local="3465328557" remote="12139730972" /><file name="inspiredgenerations.jpg" server="kitchenartcanada.com//public_html/" local="3514142865" remote="12139730972" /><file name="janod.jpg" server="kitchenartcanada.com//public_html/" local="3472135365" remote="12139730972" /><file name="juliaknight.jpg" server="kitchenartcanada.com//public_html/" local="3472491811" remote="12139730972" /><file name="klutz.jpg" server="kitchenartcanada.com//public_html/" local="3465338435" remote="12139730972" /><file name="koziol.jpg" server="kitchenartcanada.com//public_html/" local="3472065248" remote="12139730972" /><file name="kuhnrikon.jpg" server="kitchenartcanada.com//public_html/" local="3465338777" remote="12139730972" /><file name="l-objet.jpg" server="kitchenartcanada.com//public_html/" local="3467144857" remote="12139730972" /><file name="ladyjayne.jpg" server="kitchenartcanada.com//public_html/" local="3467145254" remote="12139730972" /><file name="lenox.jpg" server="kitchenartcanada.com//public_html/" local="3472065207" remote="12139730972" /><file name="lenox175.jpg" server="kitchenartcanada.com//public_html/" local="3465338168" remote="12139730972" /><file name="leonardo.jpg" server="kitchenartcanada.com//public_html/" local="3465406674" remote="12139730972" /><file name="luminarc.jpg" server="kitchenartcanada.com//public_html/" local="3472491463" remote="12139730972" /><file name="magicmill.jpg" server="kitchenartcanada.com//public_html/" local="3465406654" remote="12139730972" /><file name="magna-tiles.jpg" server="kitchenartcanada.com//public_html/" local="3472065143" remote="12139730972" /><file name="maryjurek.jpg" server="kitchenartcanada.com//public_html/" local="3472065132" remote="12139730972" /><file name="melissaanddoug.jpg" server="kitchenartcanada.com//public_html/" local="3465406614" remote="12139730972" /><file name="metalacelogo1175.jpg" server="kitchenartcanada.com//public_html/" local="3465940982" remote="12139730972" /><file name="michaelwainwright.jpg" server="kitchenartcanada.com//public_html/" local="3497309487" remote="12139730972" /><file name="microplane.jpg" server="kitchenartcanada.com//public_html/" local="3467827446" remote="12139730972" /><file name="mora.jpg" server="kitchenartcanada.com//public_html/" local="3472491516" remote="12139730972" /><file name="moser.jpg" server="kitchenartcanada.com//public_html/" local="3466117115" remote="12139730972" /><file name="nachtmann.jpg" server="kitchenartcanada.com//public_html/" local="3465406549" remote="12139730972" /><file name="nordicware.jpg" server="kitchenartcanada.com//public_html/" local="3467144731" remote="12139730972" /><file name="nowdesigns.jpg" server="kitchenartcanada.com//public_html/" local="3467145214" remote="12139730972" /><file name="oliviariegel.jpg" server="kitchenartcanada.com//public_html/" local="3465407645" remote="12139730972" /><file name="orchardtoys.jpg" server="kitchenartcanada.com//public_html/" local="3465406525" remote="12139730972" /><file name="oxo.jpg" server="kitchenartcanada.com//public_html/" local="3465406496" remote="12139730972" /><file name="plusplus.jpg" server="kitchenartcanada.com//public_html/" local="3472491211" remote="12139730972" /><file name="portmeirion.jpg" server="kitchenartcanada.com//public_html/" local="3465406430" remote="12139730972" /><file name="productlink4a.png" server="kitchenartcanada.com//public_html/" local="3465339643" remote="12139730972" /><file name="quercetti.jpg" server="kitchenartcanada.com//public_html/" local="3465406349" remote="12139730972" /><file name="quest.jpg" server="kitchenartcanada.com//public_html/" local="3472065094" remote="12139730972" /><file name="rainbowloom.jpg" server="kitchenartcanada.com//public_html/" local="3467826305" remote="12139730972" /><file name="ravensburger.jpg" server="kitchenartcanada.com//public_html/" local="3465406307" remote="12139730972" /><file name="rcr.jpg" server="kitchenartcanada.com//public_html/" local="3472065061" remote="12139730972" /><file name="rcrcrystal.jpg" server="kitchenartcanada.com//public_html/" local="3472135200" remote="12139730972" /><file name="Rogaska.jpg" server="kitchenartcanada.com//public_html/" local="3472149175" remote="12139730972" /><file name="royalworcester.jpg" server="kitchenartcanada.com//public_html/" local="3473115810" remote="12139730972" /><file name="rsvp.jpg" server="kitchenartcanada.com//public_html/" local="3465406278" remote="12139730972" /><file name="sagaform.jpg" server="kitchenartcanada.com//public_html/" local="3465406187" remote="12139730972" /><file name="sistema.jpg" server="kitchenartcanada.com//public_html/" local="3472064939" remote="12139730972" /><file name="smartgames.jpg" server="kitchenartcanada.com//public_html/" local="3472064898" remote="12139730972" /><file name="spicebox.jpg" server="kitchenartcanada.com//public_html/" local="3539037193" remote="12139730972" /><file name="splendide.jpg" server="kitchenartcanada.com//public_html/" local="3472562160" remote="12139730972" /><file name="steelforme.jpg" server="kitchenartcanada.com//public_html/" local="3497308193" remote="12139730972" /><file name="thinkfun.jpg" server="kitchenartcanada.com//public_html/" local="3472066596" remote="12139730972" /><file name="tinylove.jpg" server="kitchenartcanada.com//public_html/" local="3465406117" remote="12139730972" /><file name="tramontina.jpg" server="kitchenartcanada.com//public_html/" local="3465406080" remote="12139730972" /><file name="victorinox.jpg" server="kitchenartcanada.com//public_html/" local="3472062199" remote="12139730972" /><file name="vidivi.jpg" server="kitchenartcanada.com//public_html/" local="3472064868" remote="12139730972" /><file name="wildeye.jpg" server="kitchenartcanada.com//public_html/" local="3472491660" remote="12139730972" /><file name="wilton.jpg" server="kitchenartcanada.com//public_html/" local="3467144928" remote="12139730972" /><file name="yairemanuel.jpg" server="kitchenartcanada.com//public_html/" local="3471376331" remote="12139730972" /><file name="yamazaki.jpg" server="kitchenartcanada.com//public_html/" local="3465405915" remote="12139730972" /><file name="zoku.jpg" server="kitchenartcanada.com//public_html/" local="3472149089" remote="12139730972" /><file name="zyliss.jpg" server="kitchenartcanada.com//public_html/" local="3465405886" remote="12139730972" /></dwsync>